django_vagrantize-0.1.0.dist-info/DESCRIPTION.rst
django_vagrantize-0.1.0.dist-info/WHEEL
django_vagrantize-0.1.0.dist-info/RECORD
django_vagrantize-0.1.0.dist-info/metadata.json
django_vagrantize-0.1.0.dist-info/METADATA
django_vagrantize-0.1.0.dist-info/top_level.txt
vagrantize/__init__.py
vagrantize/models.py
vagrantize/management/__init__.py
vagrantize/management/commands/run.py
vagrantize/management/commands/__init__.py
