Metadata-Version: 2.0
Name: django-vagrantize
Version: 0.1.0
Summary: Run Django dev server from VM
Home-page: UNKNOWN
Author: Chuck Bassett
Author-email: iamchuckb@gmail.com
License: MIT License
Keywords: vagrant django runserver
Platform: UNKNOWN
Classifier: Development Status :: 3 - Alpha
Classifier: Environment :: Web Environment
Classifier: Framework :: Django
Classifier: Intended Audience :: Developers
Classifier: License :: OSI Approved :: MIT License
Classifier: Operating System :: OS Independent
Classifier: Programming Language :: Python
Classifier: Topic :: Internet :: WWW/HTTP
Classifier: Topic :: Internet :: WWW/HTTP :: Dynamic Content
Requires-Dist: django
